flac2mp3/__init__.py
flac2mp3/custom_functions.py
flac2mp3/main.py
flac2mp3_cli-1.1.1.dist-info/licenses/LICENSE
flac2mp3_cli-1.1.1.dist-info/METADATA
flac2mp3_cli-1.1.1.dist-info/WHEEL
flac2mp3_cli-1.1.1.dist-info/entry_points.txt
flac2mp3_cli-1.1.1.dist-info/top_level.txt
flac2mp3_cli-1.1.1.dist-info/RECORD
