Metadata-Version: 2.4
Name: flac2mp3-cli
Version: 1.1.1
Summary: A Python CLI tool to convert FLAC to MP3
Home-page: https://github.com/rimaout/flac2mp3
Author: rimaout
License: MIT
Keywords: python,audio coverter,flac,mp3,multithreading
Classifier: License :: OSI Approved :: MIT License
Classifier: Programming Language :: Python :: 3
Classifier: Operating System :: MacOS :: MacOS X
Classifier: Operating System :: Microsoft :: Windows
Classifier: Operating System :: POSIX :: Linux
License-File: LICENSE
Requires-Dist: alive_progress
Requires-Dist: mutagen
Dynamic: author
Dynamic: classifier
Dynamic: description
Dynamic: description-content-type
Dynamic: home-page
Dynamic: keywords
Dynamic: license
Dynamic: license-file
Dynamic: requires-dist
Dynamic: summary
